latimes/__init__.py
latimes/__main__.py
latimes/config.py
latimes/exceptions.py
latimes/latimes.py
latimes-0.3.2.dist-info/entry_points.txt
latimes-0.3.2.dist-info/WHEEL
latimes-0.3.2.dist-info/METADATA
latimes-0.3.2.dist-info/RECORD
