Metadata-Version: 2.1
Name: latimes
Version: 0.3.2
Summary: Convierte tiempos
License: MIT
Author: Antonio Feregrino
Author-email: antonio.feregrino@gmail.com
Requires-Python: >=3.6,<4.0
Classifier: License :: OSI Approved :: MIT License
Classifier: Programming Language :: Python :: 3
Classifier: Programming Language :: Python :: 3.6
Classifier: Programming Language :: Python :: 3.7
Classifier: Programming Language :: Python :: 3.8
Classifier: Programming Language :: Python :: 3.9
Requires-Dist: PyYAML (>=5.4.1,<6.0.0)
Requires-Dist: Unidecode (>=1.2.0,<2.0.0)
Requires-Dist: click (>=7.1.2,<8.0.0)
Requires-Dist: pyperclip (>=1.8.2,<2.0.0)
Requires-Dist: python-dateutil (>=2.8.1,<3.0.0)
Requires-Dist: pytz (>=2021.1,<2022.0)
